{
    "Carpincho": {
        "LastMatch": "<img src='https://frontend.cdn.aoe2companion.com/public/aoe2/de/maps/rm_yucatan.png' width='150rem' alt=''>",
        "DownloadRecLink": "<a class='align-self-center link-light link-offset-2 link-underline-opacity-25 link-underline-opacity-100-hover' href='https://aoe.ms/replay/?gameId=370103083&profileId=6237950'>Download &#128190;</a>",
        "Team 1": "EzQL| Druminado (1247) - Celts &#128081;<br>EzQL| Lordhuaiqui (1118) - Chinese &#128081;<br>EzQL| Maestro (1163) - Burgundians &#128081;<br>EzQL| isra10 (1272) - Mongols &#128081;",
        "Team 2": "Nanox (1158) - Mayans &#128128;<br>Carpincho (1243) - Burgundians &#128128;<br>Sir Monkey (1155) - Khmer &#128128;<br>dicopatito (1262) - Tatars &#128128;"
    },
    "Dicopatito": {
        "LastMatch": "<img src='https://frontend.cdn.aoe2companion.com/public/aoe2/de/maps/rm_yucatan.png' width='150rem' alt=''>",
        "DownloadRecLink": "<a class='align-self-center link-light link-offset-2 link-underline-opacity-25 link-underline-opacity-100-hover' href='https://aoe.ms/replay/?gameId=370103083&profileId=439001'>Download &#128190;</a>",
        "Team 1": "EzQL| isra10 (1272) - Mongols &#128081;<br>EzQL| Lordhuaiqui (1118) - Chinese &#128081;<br>EzQL| Maestro (1163) - Burgundians &#128081;<br>EzQL| Druminado (1247) - Celts &#128081;",
        "Team 2": "dicopatito (1262) - Tatars &#128128;<br>Sir Monkey (1155) - Khmer &#128128;<br>Carpincho (1243) - Burgundians &#128128;<br>Nanox (1158) - Mayans &#128128;"
    },
    "Nanox": {
        "LastMatch": "<img src='https://frontend.cdn.aoe2companion.com/public/aoe2/de/maps/rm_oasis.png' width='150rem' alt=''>",
        "DownloadRecLink": "<a class='align-self-center link-light link-offset-2 link-underline-opacity-25 link-underline-opacity-100-hover' href='https://aoe.ms/replay/?gameId=370510231&profileId=21582578'>Download &#128190;</a>",
        "Team 1": "Serpent23 (1215) - Britons &#128081;<br>Nanox (1175) - Mayans &#128081;<br>Sir Monkey (1146) - Khmer &#128081;<br>UzuI (1231) - Vietnamese &#128081;",
        "Team 2": "Civic (1188) - Mongols &#128128;<br>chantroikhatvong (1154) - Khmer &#128128;<br>sTaRt 2 own (1172) - Mayans &#128128;<br>L\u00e3o Nh\u1ecb (1374) - Portuguese &#128128;"
    },
    "SirMonkey": {
        "LastMatch": "<img src='https://frontend.cdn.aoe2companion.com/public/aoe2/de/maps/rm_arena.png' width='150rem' alt=''>",
        "DownloadRecLink": "<a class='align-self-center link-light link-offset-2 link-underline-opacity-25 link-underline-opacity-100-hover' href='https://aoe.ms/replay/?gameId=370541252&profileId=10739159'>Download &#128190;</a>",
        "Team 1": "\u59ec\u677e\u5b66\u9662\u7b2c\u4e00\u6218\u7565\u5bb60\u5730\u5b81\u5b81 (1206) - Britons &#128081;<br>\u54ea\u6ce2\u4f60\u62c9\u626f\u4e86 (1336) - Vikings &#128081;<br>\u65e0\u53ef\u56f0 \u6280\u4e07\u5343 \u5c81\u4e0d\u4e0e \u5929\u5149\u73b0 \u79ef\u6b64\u52bf \u5251\u8c2a\u4ed9 (1195) - Khmer &#128081;<br>Videte ne quis sciat (1075) - Bengalis &#128081;",
        "Team 2": "adinkte (1205) - Teutons &#128128;<br>Potro Occidental (1205) - Cumans &#128128;<br>Sir Monkey (1167) - Malay &#128128;<br>Arda Asar (1213) - Tatars &#128128;"
    }
}