{
    "Carpincho": {
        "LastMatch": "<img src='https://frontend.cdn.aoe2companion.com/public/aoe2/de/maps/rm_amazon_tunnels.png' width='150rem' alt=''>",
        "DownloadRecLink": "<a class='align-self-center link-light link-offset-2 link-underline-opacity-25 link-underline-opacity-100-hover' href='https://aoe.ms/replay/?gameId=395771896&profileId=1205505'>Download &#128190;</a>",
        "Team 1": "Carpincho (1250) - Bohemians &#128081;<br>Sir Monkey (1087) - Khmer &#128081;<br>Nanox (1059) - Hindustanis &#128081;<br>dicopatito (1159) - Burmese &#128081;",
        "Team 2": "Alessa (1080) - Persians &#128128;<br>ZerohLife (1125) - Chinese &#128128;<br>Ehrcander (1103) - Magyars &#128128;<br>Luxso (1099) - Portuguese &#128128;"
    },
    "Dicopatito": {
        "LastMatch": "<img src='https://frontend.cdn.aoe2companion.com/public/aoe2/de/maps/rm_nomad.png' width='150rem' alt=''>",
        "DownloadRecLink": "<a class='align-self-center link-light link-offset-2 link-underline-opacity-25 link-underline-opacity-100-hover' href='https://aoe.ms/replay/?gameId=408651317&profileId=9958277'>Download &#128190;</a>",
        "Team 1": "dicopatito (1324) - Dravidians &#128081;<br>Spider2YBanana (1389) - Maya &#128081;<br>Asgard (1352) - Wu &#128081;",
        "Team 2": "_El_Azote_De_Dios_ (1327) - Burmese &#128128;<br>ABCDEFGHIJKLMNOPQRS (1387) - Aztecs &#128128;<br>BladeY (1395) - Dravidians &#128128;"
    },
    "Nanox": {
        "LastMatch": "<img src='https://frontend.cdn.aoe2companion.com/public/aoe2/de/maps/rm_black-forest.png' width='150rem' alt=''>",
        "DownloadRecLink": "<a class='align-self-center link-light link-offset-2 link-underline-opacity-25 link-underline-opacity-100-hover' href='https://aoe.ms/replay/?gameId=408030039&profileId=18899093'>Download &#128190;</a>",
        "Team 1": "special3220 (1000) - Britons &#128081;<br>Osman (1027) - Japanese &#128081;<br>Nanox (1090) - Turks &#128081;<br>Sir Monkey (1006) - Khmer &#128081;",
        "Team 2": "DobleP (972) - Bohemians &#128128;<br>Triceratops (971) - Khmer &#128128;<br>LA MAQUINA SANCHEZ (936) - Goths &#128128;<br>Set (960) - Persians &#128128;"
    },
    "SirMonkey": {
        "LastMatch": "<img src='https://frontend.cdn.aoe2companion.com/public/aoe2/de/maps/rm_african_clearing.png' width='150rem' alt=''>",
        "DownloadRecLink": "<a class='align-self-center link-light link-offset-2 link-underline-opacity-25 link-underline-opacity-100-hover' href='https://aoe.ms/replay/?gameId=408655361&profileId=10267457'>Download &#128190;</a>",
        "Team 1": "[WWW - KT] Er MaRdiTho! (1145) - Huns &#128355<br>Ruso (1143) - Mongols &#128355<br>Roa_3 (1160) - Khmer &#128355<br>tona1410 (1113) - Italians &#128355",
        "Team 2": "Sir Monkey (1106) - Khmer &#128355<br>\u4f86\u90fd\u4f86\u4e86 (1160) - Vietnamese &#128355<br>Mr. Siege (1178) - Celts &#128355<br>Chef (1146) - Mongols &#128355"
    }
}