{
    "Carpincho": {
        "LastMatch": "<img src='https://frontend.cdn.aoe2companion.com/public/aoe2/de/maps/rm_nomad.png' width='150rem' alt=''>",
        "DownloadRecLink": "<a class='align-self-center link-light link-offset-2 link-underline-opacity-25 link-underline-opacity-100-hover' href='https://aoe.ms/replay/?gameId=382581178&profileId=9497610'>Download &#128190;</a>",
        "Team 1": "Sir Monkey (1183) - Vietnamese &#128355<br>Nanox (1141) - Huns &#128355<br>Carpincho (1194) - Persians &#128355<br>dicopatito (1178) - Spanish &#128355",
        "Team 2": "heichan000002 (1165) - Persians &#128355<br>OneHandMen (1126) - Berbers &#128355<br>djsuperguillermo (1167) - Spanish &#128355<br>\u53eb\u6211\u4e00\u58f0\u9753\u4ed4 (1155) - Mongols &#128355"
    },
    "Dicopatito": {
        "LastMatch": "<img src='https://frontend.cdn.aoe2companion.com/public/aoe2/de/maps/rm_nomad.png' width='150rem' alt=''>",
        "DownloadRecLink": "<a class='align-self-center link-light link-offset-2 link-underline-opacity-25 link-underline-opacity-100-hover' href='https://aoe.ms/replay/?gameId=382581178&profileId=10930163'>Download &#128190;</a>",
        "Team 1": "dicopatito (1178) - Spanish &#128355<br>Carpincho (1194) - Persians &#128355<br>Sir Monkey (1183) - Vietnamese &#128355<br>Nanox (1141) - Huns &#128355",
        "Team 2": "\u53eb\u6211\u4e00\u58f0\u9753\u4ed4 (1155) - Mongols &#128355<br>djsuperguillermo (1167) - Spanish &#128355<br>OneHandMen (1126) - Berbers &#128355<br>heichan000002 (1165) - Persians &#128355"
    },
    "Nanox": {
        "LastMatch": "<img src='https://frontend.cdn.aoe2companion.com/public/aoe2/de/maps/rm_nomad.png' width='150rem' alt=''>",
        "DownloadRecLink": "<a class='align-self-center link-light link-offset-2 link-underline-opacity-25 link-underline-opacity-100-hover' href='https://aoe.ms/replay/?gameId=382581178&profileId=10930163'>Download &#128190;</a>",
        "Team 1": "Sir Monkey (1183) - Vietnamese &#128355<br>dicopatito (1178) - Spanish &#128355<br>Carpincho (1194) - Persians &#128355<br>Nanox (1141) - Huns &#128355",
        "Team 2": "\u53eb\u6211\u4e00\u58f0\u9753\u4ed4 (1155) - Mongols &#128355<br>djsuperguillermo (1167) - Spanish &#128355<br>OneHandMen (1126) - Berbers &#128355<br>heichan000002 (1165) - Persians &#128355"
    },
    "SirMonkey": {
        "LastMatch": "<img src='https://frontend.cdn.aoe2companion.com/public/aoe2/de/maps/rm_nomad.png' width='150rem' alt=''>",
        "DownloadRecLink": "<a class='align-self-center link-light link-offset-2 link-underline-opacity-25 link-underline-opacity-100-hover' href='https://aoe.ms/replay/?gameId=382581178&profileId=9497610'>Download &#128190;</a>",
        "Team 1": "Sir Monkey (1183) - Vietnamese &#128355<br>Nanox (1141) - Huns &#128355<br>Carpincho (1194) - Persians &#128355<br>dicopatito (1178) - Spanish &#128355",
        "Team 2": "heichan000002 (1165) - Persians &#128355<br>OneHandMen (1126) - Berbers &#128355<br>djsuperguillermo (1167) - Spanish &#128355<br>\u53eb\u6211\u4e00\u58f0\u9753\u4ed4 (1155) - Mongols &#128355"
    }
}