{
    "Carpincho": {
        "LastMatch": "<b>Last Match</b><br>Map: Mediterranean.rms<br>",
        "Team 1": "rusguillermo (1154) - Mongols &#128128;<br>Alfil (1161) - Hindustanis &#128128;<br>Tulkas (1149) - Khmer &#128128;<br>fblumetti (1133) - Ethiopians &#128128;",
        "Team 2": "Carpincho (1137) - Mongols &#128081;<br>Sir Monkey (1205) - Khmer &#128081;<br>dicopatito (1142) - Poles &#128081;<br>Nanox (1159) - Hindustanis &#128081;",
        "DownloadRecLink": "<a class='align-self-center link-light link-offset-2 link-underline-opacity-25 link-underline-opacity-100-hover' href='https://aoe.ms/replay/?gameId=353190353&profileId=439001'>Download Rec</a>"
    },
    "Dicopatito": {
        "LastMatch": "<b>Last Match</b><br>Map: Mediterranean.rms<br>",
        "Team 1": "rusguillermo (1154) - Mongols &#128128;<br>Alfil (1161) - Hindustanis &#128128;<br>Tulkas (1149) - Khmer &#128128;<br>fblumetti (1133) - Ethiopians &#128128;",
        "Team 2": "Carpincho (1137) - Mongols &#128081;<br>Sir Monkey (1205) - Khmer &#128081;<br>dicopatito (1142) - Poles &#128081;<br>Nanox (1159) - Hindustanis &#128081;",
        "DownloadRecLink": "<a class='align-self-center link-light link-offset-2 link-underline-opacity-25 link-underline-opacity-100-hover' href='https://aoe.ms/replay/?gameId=353190353&profileId=439001'>Download Rec</a>"
    },
    "SirMonkey": {
        "LastMatch": "<b>Last Match</b><br>Map: LandNomad.rms<br>",
        "Team 2": "Nanox (1168) - Huns &#128128;<br>Sir Monkey (1199) - Khmer &#128128;<br>Alpenhime (1187) - Tatars &#128128;<br>Chris.S (1222) - Mongols &#128128;",
        "Team 1": "kat_not_dog (1155) - Japanese &#128081;<br>GREATWHITE (1154) - Tatars &#128081;<br>fidel8a (1187) - Lithuanians &#128081;<br>\u7206\u6c41\u756a\u8304 (1232) - Mongols &#128081;",
        "DownloadRecLink": "<a class='align-self-center link-light link-offset-2 link-underline-opacity-25 link-underline-opacity-100-hover' href='https://aoe.ms/replay/?gameId=353823904&profileId=8941710'>Download Rec</a>"
    },
    "Nanox": {
        "LastMatch": "<b>Last Match</b><br>Map: LandNomad.rms<br>",
        "Team 2": "Nanox (1168) - Huns &#128128;<br>Sir Monkey (1199) - Khmer &#128128;<br>Alpenhime (1187) - Tatars &#128128;<br>Chris.S (1222) - Mongols &#128128;",
        "Team 1": "kat_not_dog (1155) - Japanese &#128081;<br>GREATWHITE (1154) - Tatars &#128081;<br>fidel8a (1187) - Lithuanians &#128081;<br>\u7206\u6c41\u756a\u8304 (1232) - Mongols &#128081;",
        "DownloadRecLink": "<a class='align-self-center link-light link-offset-2 link-underline-opacity-25 link-underline-opacity-100-hover' href='https://aoe.ms/replay/?gameId=353823904&profileId=8941710'>Download Rec</a>"
    }
}