{
    "Carpincho": {
        "LastMatch": "<img src='https://frontend.cdn.aoe2companion.com/public/aoe2/de/maps/rm_amazon_tunnels.png' width='150rem' alt=''>",
        "DownloadRecLink": "<a class='align-self-center link-light link-offset-2 link-underline-opacity-25 link-underline-opacity-100-hover' href='https://aoe.ms/replay/?gameId=395771896&profileId=1205505'>Download &#128190;</a>",
        "Team 1": "Carpincho (1250) - Bohemians &#128081;<br>Sir Monkey (1087) - Khmer &#128081;<br>Nanox (1059) - Hindustanis &#128081;<br>dicopatito (1159) - Burmese &#128081;",
        "Team 2": "Alessa (1080) - Persians &#128128;<br>ZerohLife (1125) - Chinese &#128128;<br>Ehrcander (1103) - Magyars &#128128;<br>Luxso (1099) - Portuguese &#128128;"
    },
    "Dicopatito": {
        "LastMatch": "<img src='https://frontend.cdn.aoe2companion.com/public/aoe2/de/maps/rm_arena.png' width='150rem' alt=''>",
        "DownloadRecLink": "<a class='align-self-center link-light link-offset-2 link-underline-opacity-25 link-underline-opacity-100-hover' href='https://aoe.ms/replay/?gameId=406580387&profileId=10053490'>Download &#128190;</a>",
        "Team 1": "Edward Longshaft (1418) - Portuguese &#128355<br>alkongaming_2 (None) - Celts &#128355<br>Tenziki (1447) - Byzantines &#128355<br>Hand Banana (1512) - Aztecs &#128355",
        "Team 2": "Silver (1420) - Berbers &#128355<br>ChicosQLloran12 (1416) - Gurjaras &#128355<br>dicopatito (1376) - Chinese &#128355<br>Moerbsle (1442) - Wei &#128355"
    },
    "Nanox": {
        "LastMatch": "<img src='https://frontend.cdn.aoe2companion.com/public/aoe2/de/maps/rm_arena.png' width='150rem' alt=''>",
        "DownloadRecLink": "<a class='align-self-center link-light link-offset-2 link-underline-opacity-25 link-underline-opacity-100-hover' href='https://aoe.ms/replay/?gameId=406537298&profileId=439001'>Download &#128190;</a>",
        "Team 1": "Southern Knight (1006) - Khmer &#128128;<br>AttilaTheKilla (1153) - Italians &#128128;<br>NITRO_OF_THE_OLD_DOMINION (1097) - Teutons &#128128;<br>ITHero1 (1010) - Romans &#128128;",
        "Team 2": "CD JJ | Bizantino (1077) - Wei &#128081;<br>darienvasquez95 (1062) - Persians &#128081;<br>Sir Monkey (1075) - Khmer &#128081;<br>Nanox (1083) - Huns &#128081;"
    },
    "SirMonkey": {
        "LastMatch": "<img src='https://frontend.cdn.aoe2companion.com/public/aoe2/de/maps/rm_migration.png' width='150rem' alt=''>",
        "DownloadRecLink": "<a class='align-self-center link-light link-offset-2 link-underline-opacity-25 link-underline-opacity-100-hover' href='https://aoe.ms/replay/?gameId=406577601&profileId=4547800'>Download &#128190;</a>",
        "Team 1": "A PIZZAGANGSTER (1076) - Khmer &#128128;<br>ptom (992) - Vikings &#128128;<br>Sir Monkey (1063) - Dravidians &#128128;<br>\u8001\u725b (1035) - Teutons &#128128;",
        "Team 2": "lorenz.pagliari (1041) - Chinese &#128081;<br>_ Venom _ (1007) - Celts &#128081;<br>\u7dad\u5c3c (1019) - Burgundians &#128081;<br>Adel (1006) - Bohemians &#128081;"
    }
}